amrita_plugin_omikuji/__init__.py
amrita_plugin_omikuji/cache.py
amrita_plugin_omikuji/commands.py
amrita_plugin_omikuji/config.py
amrita_plugin_omikuji/llm_tool.py
amrita_plugin_omikuji/models.py
amrita_plugin_omikuji/sql_models.py
amrita_plugin_omikuji/utils.py
amrita_plugin_omikuji-0.1.1.1.dist-info/licenses/LICENSE
amrita_plugin_omikuji-0.1.1.1.dist-info/METADATA
amrita_plugin_omikuji-0.1.1.1.dist-info/WHEEL
amrita_plugin_omikuji-0.1.1.1.dist-info/top_level.txt
amrita_plugin_omikuji-0.1.1.1.dist-info/RECORD
