Metadata-Version: 2.4
Name: amrita-plugin-omikuji
Version: 0.1.1.1
Summary: AmritaBot的御神签插件
License-Expression: GPL-3.0-or-later
Project-URL: Homepage, https://github.com/AmritaBot/amrita_plugin_omikuji
Project-URL: Source, https://github.com/AmritaBot/amrita_plugin_omikuji
Project-URL: Issue Tracker, https://github.com/AmritaBot/amrita_plugin_omikuji/issues
Keywords: chat",  "nonebot
Requires-Python: <4.0,>=3.10
License-File: LICENSE
Requires-Dist: nonebot2[fastapi]>=2.4.3
Requires-Dist: nonebot-adapter-onebot>=2.4.6
Requires-Dist: nonebot-plugin-localstore>=0.7.4
Requires-Dist: aiofiles>=24.1.0
Requires-Dist: nonebot-plugin-orm>=0.8.2
Requires-Dist: amrita[full]>=0.4.4
Requires-Dist: zipp>=3.23.0
Dynamic: license-file
